flask_colorpicker/__init__.py
flask_colorpicker-0.11.dist-info/licenses/LICENSE
flask_colorpicker-0.11.dist-info/METADATA
flask_colorpicker-0.11.dist-info/WHEEL
flask_colorpicker-0.11.dist-info/top_level.txt
flask_colorpicker-0.11.dist-info/RECORD
