Metadata-Version: 2.4
Name: Flask-Colorpicker
Version: 0.11
Summary: color picker flask extension
Home-page: https://github.com/mrf345/flask_colorpicker/
Download-URL: https://github.com/mrf345/flask_colorpicker/archive/0.11.tar.gz
Author: Mohamed Feddad
Author-email: mrf345@gmail.com
License: MIT
Keywords: flask,extension,color,picker,spectrum,colorpicker
Platform: any
Classifier: Environment :: Web Environment
Classifier: Intended Audience :: Developers
Classifier: License :: OSI Approved :: MIT License
Classifier: Operating System :: OS Independent
Classifier: Programming Language :: Python
Classifier: Topic :: Internet :: WWW/HTTP :: Dynamic Content
Classifier: Topic :: Software Development :: Libraries :: Python Modules
License-File: LICENSE
Requires-Dist: Flask
Requires-Dist: Flask-Bootstrap
Requires-Dist: MarkupSafe
Dynamic: author
Dynamic: author-email
Dynamic: classifier
Dynamic: description
Dynamic: description-content-type
Dynamic: download-url
Dynamic: home-page
Dynamic: keywords
Dynamic: license
Dynamic: license-file
Dynamic: platform
Dynamic: requires-dist
Dynamic: summary
